mne_bids_pipeline/__init__.py
mne_bids_pipeline/_config.py
mne_bids_pipeline/_config_import.py
mne_bids_pipeline/_config_template.py
mne_bids_pipeline/_config_utils.py
mne_bids_pipeline/_decoding.py
mne_bids_pipeline/_docs.py
mne_bids_pipeline/_download.py
mne_bids_pipeline/_import_data.py
mne_bids_pipeline/_io.py
mne_bids_pipeline/_logging.py
mne_bids_pipeline/_main.py
mne_bids_pipeline/_parallel.py
mne_bids_pipeline/_reject.py
mne_bids_pipeline/_report.py
mne_bids_pipeline/_run.py
mne_bids_pipeline/_viz.py
mne_bids_pipeline/typing.py
mne_bids_pipeline/steps/__init__.py
mne_bids_pipeline/steps/freesurfer/_01_recon_all.py
mne_bids_pipeline/steps/freesurfer/_02_coreg_surfaces.py
mne_bids_pipeline/steps/freesurfer/__init__.py
mne_bids_pipeline/steps/freesurfer/contrib/LICENSE
mne_bids_pipeline/steps/freesurfer/contrib/README
mne_bids_pipeline/steps/freesurfer/contrib/run.py
mne_bids_pipeline/steps/freesurfer/contrib/version
mne_bids_pipeline/steps/init/_01_init_derivatives_dir.py
mne_bids_pipeline/steps/init/_02_find_empty_room.py
mne_bids_pipeline/steps/init/__init__.py
mne_bids_pipeline/steps/preprocessing/_01_data_quality.py
mne_bids_pipeline/steps/preprocessing/_02_head_pos.py
mne_bids_pipeline/steps/preprocessing/_03_maxfilter.py
mne_bids_pipeline/steps/preprocessing/_04_frequency_filter.py
mne_bids_pipeline/steps/preprocessing/_05_regress_artifact.py
mne_bids_pipeline/steps/preprocessing/_06a1_fit_ica.py
mne_bids_pipeline/steps/preprocessing/_06a2_find_ica_artifacts.py
mne_bids_pipeline/steps/preprocessing/_06b_run_ssp.py
mne_bids_pipeline/steps/preprocessing/_07_make_epochs.py
mne_bids_pipeline/steps/preprocessing/_08a_apply_ica.py
mne_bids_pipeline/steps/preprocessing/_08b_apply_ssp.py
mne_bids_pipeline/steps/preprocessing/_09_ptp_reject.py
mne_bids_pipeline/steps/preprocessing/__init__.py
mne_bids_pipeline/steps/sensor/_01_make_evoked.py
mne_bids_pipeline/steps/sensor/_02_decoding_full_epochs.py
mne_bids_pipeline/steps/sensor/_03_decoding_time_by_time.py
mne_bids_pipeline-1.9.0.dist-info/METADATA
mne_bids_pipeline-1.9.0.dist-info/WHEEL
mne_bids_pipeline-1.9.0.dist-info/entry_points.txt
mne_bids_pipeline-1.9.0.dist-info/licenses/LICENSE.txt
mne_bids_pipeline-1.9.0.dist-info/RECORD
