Metadata-Version: 2.3
Name: mne-bids-pipeline
Version: 1.9.0
Summary: A full-flegded processing pipeline for your MEG and EEG data
Project-URL: homepage, https://mne.tools/mne-bids-pipeline
Project-URL: repository, https://github.com/mne-tools/mne-bids-pipeline
Project-URL: changelog, http://mne.tools/mne-bids-pipeline/changes.html
Author: Eric Larson, Alexandre Gramfort, Mainak Jas
Author-email: Richard Höchenberger <richard.hoechenberger@gmail.com>
License: Copyright © 2019-2022, authors of MNE-BIDS-Pipeline
License-File: LICENSE.txt
Keywords: neuroscience,psychology,science
Classifier: Intended Audience :: Science/Research
Classifier: Programming Language :: Python
Requires-Python: >=3.10
Requires-Dist: annotated-types
Requires-Dist: autoreject
Requires-Dist: bokeh
Requires-Dist: dask[distributed]
Requires-Dist: filelock
Requires-Dist: joblib>=0.14
Requires-Dist: json-tricks
Requires-Dist: jupyter-server-proxy
Requires-Dist: matplotlib
Requires-Dist: mne-bids[full]
Requires-Dist: mne[hdf5]>=1.7
Requires-Dist: nibabel
Requires-Dist: numpy
Requires-Dist: openpyxl
Requires-Dist: packaging
Requires-Dist: pandas
Requires-Dist: psutil
Requires-Dist: pyarrow
Requires-Dist: pydantic>=2.0.0
Requires-Dist: python-picard
Requires-Dist: pyvista
Requires-Dist: pyvistaqt
Requires-Dist: qtpy
Requires-Dist: rich
Requires-Dist: scikit-learn
Requires-Dist: scipy
Requires-Dist: seaborn
Requires-Dist: threadpoolctl
Provides-Extra: docs
Requires-Dist: black; extra == 'docs'
Requires-Dist: livereload; extra == 'docs'
Requires-Dist: mike; extra == 'docs'
Requires-Dist: mkdocs; extra == 'docs'
Requires-Dist: mkdocs-exclude; extra == 'docs'
Requires-Dist: mkdocs-include-markdown-plugin; extra == 'docs'
Requires-Dist: mkdocs-macros-plugin; extra == 'docs'
Requires-Dist: mkdocs-material-extensions; extra == 'docs'
Requires-Dist: mkdocs-material>=9.0.4; extra == 'docs'
Requires-Dist: mkdocstrings-python; extra == 'docs'
Provides-Extra: tests
Requires-Dist: httpx>=0.20; extra == 'tests'
Requires-Dist: jinja2; extra == 'tests'
Requires-Dist: openneuro-py>=2022.2.0; extra == 'tests'
Requires-Dist: pooch; extra == 'tests'
Requires-Dist: psutil; extra == 'tests'
Requires-Dist: pygments; extra == 'tests'
Requires-Dist: pytest; extra == 'tests'
Requires-Dist: pytest-cov; extra == 'tests'
Requires-Dist: pyyaml; extra == 'tests'
Requires-Dist: ruff; extra == 'tests'
Requires-Dist: tqdm; extra == 'tests'
